data_snack/__init__.py
data_snack/exceptions.py
data_snack/snack.py
data_snack/utils.py
data_snack/connections/__init__.py
data_snack/connections/base.py
data_snack/connections/memcached.py
data_snack/connections/mongo.py
data_snack/connections/redis.py
data_snack/entities/__init__.py
data_snack/entities/base.py
data_snack/entities/compound.py
data_snack/entities/entity_meta.py
data_snack/entities/exceptions.py
data_snack/entities/models.py
data_snack/entities/registry.py
data_snack/entities/schema.py
data_snack/entities/utils.py
data_snack/entities/validation.py
data_snack/key_factories/__init__.py
data_snack/key_factories/base.py
data_snack/key_factories/cluster.py
data_snack/key_factories/hash.py
data_snack/key_factories/non_cluster.py
data_snack/serializers/__init__.py
data_snack/serializers/base.py
data_snack/serializers/dataclass.py
data_snack/serializers/json.py
data_snack/wrap/__init__.py
data_snack/wrap/base.py
data_snack/wrap/data_frame.py
data_snack/wrap/entity.py
data_snack/wrap/exceptions.py
data_snack-1.0.8.dist-info/LICENSE
data_snack-1.0.8.dist-info/METADATA
data_snack-1.0.8.dist-info/WHEEL
data_snack-1.0.8.dist-info/top_level.txt
data_snack-1.0.8.dist-info/RECORD
