Metadata-Version: 2.1
Name: data_snack
Version: 1.0.8
Home-page: https://github.com/webinterpret-ds/data-snack
Author: webinterpret-datascience
Author-email: data-science@webinterpret.com
Project-URL: Bug Tracker, https://github.com/webinterpret-ds/data-snack/issues
Classifier: Programming Language :: Python :: 3
Classifier: License :: OSI Approved :: GNU General Public License v3 or later (GPLv3+)
Classifier: Operating System :: OS Independent
Requires-Python: >=3.8
License-File: LICENSE
Requires-Dist: pandas>=1.3.5
Requires-Dist: pymongo==4.6.1
Provides-Extra: dynamic_entity
Requires-Dist: data-snack-dynamic-entity; extra == "dynamic-entity"
